{"type":"PR","pr":{"number":153,"head":"09c811388f7c8be84397dbe62b3ba9cce8e0514c"},"user":"ina_job","status":"pending_publish","branch":"cms/3dプリンタでゼロから作る「スピーカー」","collection":"post","title":"3Dプリンタでゼロから作る「スピーカー」","description":"3Dプリンタを使ってスピーカをゼロから作る作例を紹介します。","objects":{"entry":{"path":"site/content/post/3dプリンタでゼロから作る「スピーカー」.md","sha":"2ee9dff223dbd4a08b83e1029c62dce244ef96bf"},"files":[{"path":"/site/static/img/3dprinter-speaker.jpg","sha":"f1ea28d7066d792e3cebb88a9c7e1356223995e9"}]},"timeStamp":"2019-04-17T12:42:34.390Z"}