{"type":"PR","pr":{"number":410,"head":"78f09b249a1c297c40eb046c8cb006fac7bb2bcf"},"user":"ina_job","status":"pending_review","branch":"cms/めっちゃかっこいい自撮り用のロボットアーム","collection":"post","title":"めっちゃかっこいい自撮り用のロボットアーム","description":"かっこいい自撮り動画を実現するためのロボットアームの作例を紹介します。","objects":{"entry":{"path":"site/content/post/めっちゃかっこいい自撮り用のロボットアーム.md","sha":"f9e23d138480519e0b992654187fda4270f96763"},"files":[{"path":"/site/static/img/camera-robot.jpg","sha":"2ba91e95668aadf32d0654348d9290d2fe0eb8a4"}]},"timeStamp":"2019-09-26T13:33:54.441Z"}