{"type":"PR","pr":{"number":372,"head":"95aff0013a097f66bbc8430c623439473287b6bf"},"user":"ina_job","status":"draft","branch":"cms/ピンポン玉を使った巨大なledディスプレイ","collection":"post","title":"ピンポン玉を使った巨大なLEDディスプレイ","description":"ピンポン玉を使った巨大なLEDディスプレイの作例を紹介します。","objects":{"entry":{"path":"site/content/post/ピンポン玉を使った巨大なledディスプレイ.md","sha":"b0daa7ce6ac419f5ccabb55d05a1b06fa37a6444"},"files":[{"path":"/site/static/img/big-ping-pong-display.png","sha":"9d95c773c131575acfe46f1278b732ae2a6da6a4"}]},"timeStamp":"2019-09-08T01:08:13.056Z"}