{"type":"PR","pr":{"number":278,"head":"4c15b0e51daee70e239340506671049f201f43ae"},"user":"ina_job","status":"draft","branch":"cms/何かに似たraspberry-piケース","collection":"post","title":"何かに似たRaspberry Piケース","description":"何かによく似たデザインのRaspberry Pi ケースの作例を紹介します。","objects":{"entry":{"path":"site/content/post/何かに似たraspberry-piケース.md","sha":"c568ee486bab9131244e806f44e04389fa3a7dcd"},"files":[{"path":"/site/static/img/ras-pro.jpg","sha":"58d9fea6772e01abb31d313f502d92db67d58951"}]},"timeStamp":"2019-06-27T13:08:28.734Z"}