{"type":"PR","pr":{"number":257,"head":"e3ebc175b98025bf09298e8047117acca8c1c1b1"},"user":"ina_job","status":"pending_review","branch":"cms/表面実装ledを使った7セグメントled","collection":"post","title":"表面実装LEDを使った7セグメントLED","description":"表面実装LEDを使った7セグメントLEDの作例を紹介します。","objects":{"entry":{"path":"site/content/post/表面実装ledを使った7セグメントled.md","sha":"4f84cd4cadcb257b28a8bd47d3f01e6091d3961a"},"files":[{"path":"/site/static/img/smd-7seg.jpg","sha":"40d5358107516676024eb99e81735c927007d24f"},{"path":"/site/static/img/smd-7seg.jpg","sha":"40d5358107516676024eb99e81735c927007d24f"}]},"timeStamp":"2019-06-17T01:13:22.941Z"}