{"type":"PR","pr":{"number":881,"head":"35ff3c89bedc192b994e0c3e9bf5576608cb37a8"},"user":"ina_job","status":"pending_publish","branch":"cms/post/オープンソースのノートパソコン「reform」","collection":"post","title":"オープンソースのノートパソコン「Reform」","description":"オープンソースのノートパソコン「Reform」を紹介します。","objects":{"entry":{"path":"site/content/post/オープンソースのノートパソコン「reform」.md","sha":"de9a3792d1a5722ceb951a908271a3c593693130"},"files":[{"path":"/site/static/img/reform_v2_prototype_top.jpg","sha":"30b78f401e33e23569a977b0d1328e09c7d4ba8b"}]},"timeStamp":"2020-12-22T12:17:10.860Z","version":"1"}